stacks_textblock/__init__.py
stacks_textblock/admin.py
stacks_textblock/apps.py
stacks_textblock/models.py
stacks_textblock/serializers.py
stacks_textblock/stuff.py
stacks_textblock/migrations/0001_initial.py
stacks_textblock/migrations/0002_auto_20150407_1957.py
stacks_textblock/migrations/0003_auto_20150528_1719.py
stacks_textblock/migrations/0004_auto_20150528_1719.py
stacks_textblock/migrations/0005_auto_20150529_2033.py
stacks_textblock/migrations/__init__.py
stacks_textblock/templates/stacks_textblock/stackstextblock/stackstextblock-full_width.html
stacks_textblock/templates/stacks_textblock/stackstextblock/stackstextblock-pullquote.html
stacks_textblock/templates/stacks_textblock/stackstextblocklist/stackstextblocklist-1up.html
stacks_textblock/templates/stacks_textblock/stackstextblocklist/stackstextblocklist-2up.html
stacks_textblock/templates/stacks_textblock/stackstextblocklist/stackstextblocklist-3up.html
stacks_textblock-0.2.dist-info/DESCRIPTION.rst
stacks_textblock-0.2.dist-info/LICENSE.txt
stacks_textblock-0.2.dist-info/METADATA
stacks_textblock-0.2.dist-info/metadata.json
stacks_textblock-0.2.dist-info/RECORD
stacks_textblock-0.2.dist-info/top_level.txt
stacks_textblock-0.2.dist-info/WHEEL
tests/__init__.py
tests/test_settings.py
tests/tests.py
tests/urls.py
